wattson_abstract_rtu/__init__.py
wattson_abstract_rtu/backend_interface.py
wattson_abstract_rtu/util.py
wattson_abstract_rtu-1.0.1.dist-info/LICENSE
wattson_abstract_rtu-1.0.1.dist-info/METADATA
wattson_abstract_rtu-1.0.1.dist-info/WHEEL
wattson_abstract_rtu-1.0.1.dist-info/top_level.txt
wattson_abstract_rtu-1.0.1.dist-info/RECORD
