Metadata-Version: 2.1
Name: wattson-abstract-rtu
Version: 1.0.1
Summary: An abstraction layer for software-based RTU implementations.
Home-page: https://github.com/fkie-cad/wattson-abstract-rtu
Author: Olav Lamberts and Lennart Bader
Author-email: lennart.bader@fkie.fraunhofer.de
License: UNKNOWN
Platform: UNKNOWN
Classifier: Programming Language :: Python :: 3
Classifier: License :: OSI Approved :: MIT License
Classifier: Operating System :: OS Independent
Requires-Python: >=3.7
